magpurify/__init__.py
magpurify/cli.py
magpurify/utilities.py
magpurify/modules/__init__.py
magpurify/modules/clade.py
magpurify/modules/clean.py
magpurify/modules/conspecific.py
magpurify/modules/contam.py
magpurify/modules/coverage.py
magpurify/modules/gc.py
magpurify/modules/phylo.py
magpurify/modules/tetra.py
magpurify-2.1.2.dist-info/LICENSE
magpurify-2.1.2.dist-info/METADATA
magpurify-2.1.2.dist-info/WHEEL
magpurify-2.1.2.dist-info/entry_points.txt
magpurify-2.1.2.dist-info/top_level.txt
magpurify-2.1.2.dist-info/RECORD
