Metadata-Version: 2.1
Name: magpurify
Version: 2.1.2
Summary: Identify and remove incorrectly binned contigs from metagenome-assembled genomes.
Home-page: https://github.com/snayfach/MAGpurify
Author: Stephen Nayfach, Antonio Pedro Camargo
License: GNU General Public License v3.0
Keywords: bioinformatics,metagenomics,metagenome-assembled genomes
Platform: UNKNOWN
Classifier: Intended Audience :: Science/Research
Classifier: Natural Language :: English
Classifier: Topic :: Software Development :: Libraries
Classifier: Topic :: Scientific/Engineering :: Bio-Informatics
Classifier: License :: OSI Approved :: GNU General Public License (GPL)
Classifier: Programming Language :: Python :: 3
Requires-Python: >=3.6
Requires-Dist: biopython
Requires-Dist: numpy
Requires-Dist: pandas
Requires-Dist: scikit-learn
